{
  "runs": [
    {
      "term_scoring_type": "",
      "scoring_method_type": "unigram",
      "name_format": "%s-unigram_mle",
      "t_param": [""],
      "t_start": [1],
      "t_end": [1],
      "t_increment": [1],
      "m_param": [""],
      "m_start": [1],
      "m_end": [1],
      "m_increment": [1],
      "folder_name": "mle",
      "stopwords": [],
      "stem": false
    },
    {
      "term_scoring_type": "jm",
      "scoring_method_type": "unigram",
      "name_format": "%s-unigram_jm_lambda_%.2f",
      "t_param": ["lambda"],
      "t_start": [0],
      "t_end": [1],
      "t_increment": [0.05],
      "m_param": [""],
      "m_start": [1],
      "m_end": [1],
      "m_increment": [1],
      "folder_name": "jelinek_mercer",
      "stopwords": [],
      "stem": false
    },
    {
      "term_scoring_type": "dirichlet_prior",
      "scoring_method_type": "unigram",
      "name_format": "%s-unigram_dir_mu_%.2f",
      "t_param": ["mu"],
      "t_start": [300],
      "t_end": [3000],
      "t_increment": [50],
      "m_param": [""],
      "m_start": [1],
      "m_end": [1],
      "m_increment": [1],
      "folder_name": "dirichlet_prior",
      "stopwords": [],
      "stem": false
    },
    {
      "term_scoring_type": "bm25",
      "scoring_method_type": "unigram",
      "name_format": "%s-unigram_bm25_k1_%.2f_b_%.2f",
      "t_param": ["k1", "b"],
      "t_start": [1.2, 0],
      "t_end": [3, 1],
      "t_increment": [0.05, 0.05],
      "m_param": [""],
      "m_start": [1],
      "m_end": [1],
      "m_increment": [1],
      "folder_name": "bm25",
      "stopwords": [],
      "stem": false
    },
    {
      "term_scoring_type": "tfidf",
      "scoring_method_type": "unigram",
      "name_format": "%s-unigram_tfidf",
      "t_param": [""],
      "t_start": [1],
      "t_end": [1],
      "t_increment": [1],
      "m_param": [""],
      "m_start": [1],
      "m_end": [1],
      "m_increment": [1],
      "folder_name": "tfidf",
      "stopwords": [],
      "stem": false
    }
  ]
}